generative_ai_qa/__init__.py
generative_ai_qa/generative_ai_qa.py
generative_ai_qa-0.1.1.dist-info/LICENSE
generative_ai_qa-0.1.1.dist-info/METADATA
generative_ai_qa-0.1.1.dist-info/WHEEL
generative_ai_qa-0.1.1.dist-info/top_level.txt
generative_ai_qa-0.1.1.dist-info/RECORD
