Metadata-Version: 2.2
Name: generative_ai_qa
Version: 0.1.1
Summary: A Python package for question answering using Google Generative AI.
Author: Abhinav
Author-email: abhinav.kumar@savatarr.tech
License: MIT
Classifier: Programming Language :: Python :: 3
Classifier: License :: OSI Approved :: MIT License
Classifier: Operating System :: OS Independent
Requires-Python: >=3.8
License-File: LICENSE
Requires-Dist: google-generativeai>=0.1.0
Dynamic: author
Dynamic: author-email
Dynamic: classifier
Dynamic: description
Dynamic: description-content-type
Dynamic: license
Dynamic: requires-dist
Dynamic: requires-python
Dynamic: summary
